COPYING
INSTALL
MANIFEST.in
README
TODO
setup.cfg
setup.py
data/lorem-ipsum-generator.desktop
src/.lorem_ipsum_generator_postinstall.py
src/lorem-ipsum-generator
src/testlipsum.py
src/lipsum/__init__.py
src/lipsum/data/dictionary.txt
src/lipsum/data/lipsum.xml
src/lipsum/data/sample.txt
src/lorem_ipsum_generator.egg-info/PKG-INFO
src/lorem_ipsum_generator.egg-info/SOURCES.txt
src/lorem_ipsum_generator.egg-info/dependency_links.txt
src/lorem_ipsum_generator.egg-info/top_level.txt