Metadata-Version: 1.0
Name: lorem-ipsum-generator
Version: 0.3
Summary: Generates random lorem ipsum text
Home-page: http://code.google.com/p/lorem-ipsum-generator/
Author: James Hales
Author-email: jhales.perth@gmail.com
License: BSD License
Platform: UNKNOWN
